rctf/golf/__init__.py
rctf/golf/exceptions.py
rctf/golf/util.py
rctf_golf-1.0.5.dist-info/LICENSE.txt
rctf_golf-1.0.5.dist-info/METADATA
rctf_golf-1.0.5.dist-info/WHEEL
rctf_golf-1.0.5.dist-info/top_level.txt
rctf_golf-1.0.5.dist-info/RECORD
