Metadata-Version: 2.1
Name: rctf-golf
Version: 1.0.5
Summary: a tool for developing golfing CTF challenges
Home-page: https://github.com/redpwn/rctf-golf
Author: Aaron Esau
Author-email: aaron@redpwn.net
License: UNKNOWN
Keywords: golf golfing ctf rctf ctf-platform
Platform: UNKNOWN
Requires-Dist: requests
